MANIFEST.in
README.md
requirements.txt
setup.cfg
setup.py
KGWAS.egg-info/PKG-INFO
KGWAS.egg-info/SOURCES.txt
KGWAS.egg-info/dependency_links.txt
KGWAS.egg-info/not-zip-safe
KGWAS.egg-info/requires.txt
KGWAS.egg-info/top_level.txt
kgwas/__init__.py
kgwas/conv.py
kgwas/data.py
kgwas/eval_utils.py
kgwas/kgwas.py
kgwas/kgwas_data.py
kgwas/model.py
kgwas/params.py
kgwas/utils.py
kgwas/version.py