Metadata-Version: 2.1
Name: KGWAS
Version: 0.0.2
Summary: KGWAS
Home-page: https://github.com/snap-stanford/KGWAS
Author: KGWAS Team
Author-email: kexinh@stanford.edu
License: MIT
Platform: UNKNOWN
